Metadata-Version: 1.1
Name: adamP-BioTools
Version: 1.17
Summary: Personal Tools for working with biological data
Home-page: https://github.com/adamnicolaspelletier/adamP_BioTools
Author: Adam Pelletier
Author-email: adam.nicolas.pelletier@gmail.com
License: None
Download-URL: https://github.com/adamnicolaspelletier/adamP_BioTools/archive/1.17.tar.gz
Platform: UNKNOWN
